{
  "properties": [
    {
      "name": "youtube.api-url",
      "type": "java.lang.String",
      "description": "Base URL for YouTube Data API v3 playlistItems endpoint"
    },
    {
      "name": "youtube.part",
      "type": "java.lang.String",
      "description": "Specifies the resource parts to include in the API response (e.g. snippet)"
    },
    {
      "name": "youtube.max-results",
      "type": "java.lang.Integer",
      "description": "Maximum number of results returned per API request (max 50)"
    },
    {
      "name": "youtube.api-key",
      "type": "java.lang.String",
      "description": "API key used to authenticate requests to YouTube Data API v3"
    },
    {
      "name": "spotify.client-id",
      "type": "java.lang.String",
      "description": "Spotify application Client ID used for OAuth authentication"
    },
    {
      "name": "spotify.redirect-uri",
      "type": "java.lang.String",
      "description": "Redirect URI registered in Spotify Developer Dashboard for OAuth callbacks"
    },
    {
      "name": "spotify.client-secret",
      "type": "java.lang.String",
      "description": "Spotify application Client Secret used to exchange authorization code for access token (keep it secure)"
    }
  ]
}
